Metadata-Version: 2.1
Name: odoo13-addon-l10n-es-aeat-sii-oca
Version: 13.0.2.6.0
Summary: Suministro Inmediato de Información en el IVA
Home-page: https://github.com/OCA/l10n-spain
Author: Acysos S.L.,Diagram,Minorisa,Studio73,FactorLibre,Comunitea,Otherway,Tecnativa,Javi Melendez,Odoo Community Association (OCA)
Author-email: support@odoo-community.org
License: AGPL-3
Platform: UNKNOWN
Classifier: Programming Language :: Python
Classifier: Framework :: Odoo
Classifier: Framework :: Odoo :: 13.0
Classifier: License :: OSI Approved :: GNU Affero General Public License v3
Classifier: Development Status :: 5 - Production/Stable
Requires-Python: >=3.5
Requires-Dist: odoo13-addon-account-invoice-refund-link
Requires-Dist: odoo13-addon-l10n-es-aeat
Requires-Dist: odoo13-addon-queue-job
Requires-Dist: odoo (<13.1dev,>=13.0a)
Requires-Dist: pyOpenSSL
Requires-Dist: requests
Requires-Dist: zeep
